pygeoapi_plugins/__init__.py
pygeoapi_plugins/formatter/__init__.py
pygeoapi_plugins/formatter/xml.py
pygeoapi_plugins/process/__init__.py
pygeoapi_plugins/process/intersect.py
pygeoapi_plugins/process/sitemap.py
pygeoapi_plugins/provider/__init__.py
pygeoapi_plugins/provider/ckan.py
pygeoapi_plugins/provider/filesystem_xml.py
pygeoapi_plugins/provider/geopandas_.py
pygeoapi_plugins/provider/mvt_cache.py
pygeoapi_plugins/provider/mvt_postgresql.py
pygeoapi_plugins/provider/postgresql.py
pygeoapi_plugins/provider/sparql.py
pygeoapi_plugins-0.4.0.dist-info/licenses/LICENSE
pygeoapi_plugins-0.4.0.dist-info/METADATA
pygeoapi_plugins-0.4.0.dist-info/WHEEL
pygeoapi_plugins-0.4.0.dist-info/top_level.txt
pygeoapi_plugins-0.4.0.dist-info/RECORD
