Metadata-Version: 2.4
Name: pygeoapi_plugins
Version: 0.4.0
Summary: pygeoapi plugins
Home-page: https://github.com/cgs-earth/pygeoapi-plugins
Author: Benjamin Webb
Author-email: bwebb@lincolninst.edu
Maintainer: Benjamin Webb
Maintainer-email: bwebb@lincolninst.edu
License: MIT
Keywords: cgs pygeoapi geopython
Platform: all
Classifier: Development Status :: 4 - Beta
Classifier: Environment :: Console
Classifier: Intended Audience :: Developers
Classifier: Intended Audience :: Science/Research
Classifier: License :: OSI Approved :: MIT License
Classifier: Operating System :: OS Independent
Classifier: Programming Language :: Python
Classifier: Topic :: Scientific/Engineering :: GIS
License-File: LICENSE
Requires-Dist: pygeoapi
Requires-Dist: geoalchemy
Requires-Dist: geopandas
Requires-Dist: numpy==2.0.1
Requires-Dist: psycopg2
Requires-Dist: pygeofilter[backend-sqlalchemy]
Requires-Dist: requests
Requires-Dist: shapely>=2.1.0
Requires-Dist: SPARQLWrapper
Requires-Dist: SQLAlchemy
Dynamic: author
Dynamic: author-email
Dynamic: classifier
Dynamic: description
Dynamic: description-content-type
Dynamic: home-page
Dynamic: keywords
Dynamic: license
Dynamic: license-file
Dynamic: maintainer
Dynamic: maintainer-email
Dynamic: platform
Dynamic: requires-dist
Dynamic: summary
